ai_terminal/__init__.py
ai_terminal/ai.py
ai_terminal/setup.py
hc_ai_terminal-0.5.dist-info/METADATA
hc_ai_terminal-0.5.dist-info/WHEEL
hc_ai_terminal-0.5.dist-info/entry_points.txt
hc_ai_terminal-0.5.dist-info/top_level.txt
hc_ai_terminal-0.5.dist-info/RECORD
