Metadata-Version: 2.1
Name: hc_ai_terminal
Version: 0.5
